qgans_pro/__init__.py
qgans_pro/cli.py
qgans_pro/license.py
qgans_pro/backends/__init__.py
qgans_pro/backends/base.py
qgans_pro/backends/pennylane_backend.py
qgans_pro/backends/qiskit_backend.py
qgans_pro/losses/__init__.py
qgans_pro/losses/quantum_losses.py
qgans_pro/models/__init__.py
qgans_pro/models/classical_discriminator.py
qgans_pro/models/classical_generator.py
qgans_pro/models/quantum_discriminator.py
qgans_pro/models/quantum_generator.py
qgans_pro/training/__init__.py
qgans_pro/training/trainer.py
qgans_pro/utils/__init__.py
qgans_pro/utils/data_loaders.py
qgans_pro/utils/metrics.py
qgans_pro/utils/visualization.py
quantum_generative_adversarial_networks_pro-1.0.0.dist-info/licenses/License
quantum_generative_adversarial_networks_pro-1.0.0.dist-info/METADATA
quantum_generative_adversarial_networks_pro-1.0.0.dist-info/WHEEL
quantum_generative_adversarial_networks_pro-1.0.0.dist-info/entry_points.txt
quantum_generative_adversarial_networks_pro-1.0.0.dist-info/top_level.txt
quantum_generative_adversarial_networks_pro-1.0.0.dist-info/RECORD
