Metadata-Version: 2.4
Name: quantum-generative-adversarial-networks-pro
Version: 1.0.0
Summary: Quantum-enhanced GAN framework for high-fidelity synthetic data generation
Home-page: https://github.com/krish567366/quantum-generative-adversarial-networks-pro
Author: Krishna Bajpai
Author-email: Krishna Bajpai <bajpaikrishna715@gmail.com>
License: Commercial
Project-URL: Homepage, https://github.com/krish567366/quantum-generative-adversarial-networks-pro
Project-URL: Documentation, https://krish567366.github.io/quantum-generative-adversarial-networks-pro/
Project-URL: Repository, https://github.com/krish567366/quantum-generative-adversarial-networks-pro
Project-URL: Issues, https://github.com/krish567366/quantum-generative-adversarial-networks-pro/issues
Keywords: quantum computing,generative adversarial networks,machine learning,qiskit,pennylane
Platform: any
Classifier: Development Status :: 3 - Alpha
Classifier: Intended Audience :: Developers
Classifier: Intended Audience :: Science/Research
Classifier: License :: Other/Proprietary License
Classifier: Programming Language :: Python :: 3
Classifier: Programming Language :: Python :: 3.8
Classifier: Programming Language :: Python :: 3.9
Classifier: Programming Language :: Python :: 3.10
Classifier: Programming Language :: Python :: 3.11
Classifier: Topic :: Scientific/Engineering :: Artificial Intelligence
Classifier: Topic :: Scientific/Engineering :: Physics
Requires-Python: >=3.8
License-File: License
Requires-Dist: qiskit>=1.0.0
Requires-Dist: pennylane>=0.30.0
Requires-Dist: torch>=1.12.0
Requires-Dist: torchvision>=0.13.0
Requires-Dist: numpy>=1.21.0
Requires-Dist: matplotlib>=3.5.0
Requires-Dist: scikit-learn>=1.1.0
Requires-Dist: scipy>=1.8.0
Requires-Dist: tqdm>=4.64.0
Requires-Dist: typer[all]>=0.9.0
Requires-Dist: pillow>=9.0.0
Requires-Dist: pandas>=1.4.0
Requires-Dist: seaborn>=0.11.0
Provides-Extra: docs
Requires-Dist: mkdocs>=1.5.0; extra == "docs"
Requires-Dist: mkdocs-material>=9.0.0; extra == "docs"
Requires-Dist: mkdocstrings[python]>=0.20.0; extra == "docs"
Requires-Dist: mkdocs-jupyter>=0.24.0; extra == "docs"
Provides-Extra: dev
Requires-Dist: pytest>=7.0.0; extra == "dev"
Requires-Dist: pytest-cov>=4.0.0; extra == "dev"
Requires-Dist: black>=22.0.0; extra == "dev"
Requires-Dist: isort>=5.10.0; extra == "dev"
Requires-Dist: flake8>=5.0.0; extra == "dev"
Requires-Dist: pre-commit>=2.20.0; extra == "dev"
Provides-Extra: jupyter
Requires-Dist: jupyter>=1.0.0; extra == "jupyter"
Requires-Dist: ipykernel>=6.15.0; extra == "jupyter"
Requires-Dist: ipywidgets>=8.0.0; extra == "jupyter"
Dynamic: author
Dynamic: home-page
Dynamic: license-file
Dynamic: platform
Dynamic: requires-python
